count_timer/__init__.py
count_timer/actual.py
count_timer/count_timer.py
count_timer/demo.py
count_timer/demo_asciimatics.py
count_timer/demo_async.py
count_timer/demo_async_2.py
count_timer/demo_asyncio.py
count_timer/demo_austin.py
count_timer/demo_prompt_toolkit.py
count_timer/demo_pycui.py
count_timer/demo_textual.py
count_timer/demo_thread.py
count_timer/quickstart.py
tests/__init__.py
tests/conftest.py
tests/test_count_timers.py
count_timer-0.3.8.dist-info/METADATA
count_timer-0.3.8.dist-info/WHEEL
count_timer-0.3.8.dist-info/entry_points.txt
count_timer-0.3.8.dist-info/top_level.txt
count_timer-0.3.8.dist-info/RECORD
