Metadata-Version: 2.1
Name: count-timer
Version: 0.3.8
Summary: A count-timer with optional expiry that can be paused, resumed, and reset.
Home-page: https://github.com/jeffwright13/count-timer
Author: Jeff Wright
Author-email: jeff.washcloth@gmail.com
License: MIT
Keywords: python counter timer count-timer count_timer
Classifier: Development Status :: 4 - Beta
Classifier: Intended Audience :: Developers
Classifier: Topic :: Software Development :: Testing
Classifier: Programming Language :: Python :: 3.7
Classifier: Programming Language :: Python :: 3.8
Classifier: Programming Language :: Python :: 3.9
Classifier: Programming Language :: Python :: 3.10
Classifier: Operating System :: OS Independent
Classifier: License :: OSI Approved :: MIT License
Requires-Python: >=3.7
Requires-Dist: blessed (>=1.19.1)
